vidme/__init__.py
vidme/client.py
vidme/gateway.py
vidme/users.py
vidme/videos.py
vidme.py-0.1.0.dev2.dist-info/DESCRIPTION.rst
vidme.py-0.1.0.dev2.dist-info/METADATA
vidme.py-0.1.0.dev2.dist-info/RECORD
vidme.py-0.1.0.dev2.dist-info/WHEEL
vidme.py-0.1.0.dev2.dist-info/metadata.json
vidme.py-0.1.0.dev2.dist-info/top_level.txt
