Metadata-Version: 2.0
Name: vidme.py
Version: 0.1.0.dev2
Summary: A python wrapper for the Vidme API
Home-page: https://github.com/Zakru/vidme.py
Author: Zakru
Author-email: sakari.leukkunen@gmail.com
License: MIT
Keywords: vidme api wrapper
Platform: UNKNOWN
Classifier: Development Status :: 1 - Planning
Classifier: Intended Audience :: Developers
Classifier: Topic :: Software Development
Classifier: License :: OSI Approved :: MIT License
Classifier: Programming Language :: Python :: 3
Requires-Python: >=3
Requires-Dist: requests
